bridge_iq/__init__.py
bridge_iq/client.py
bridge_iq/environment.py
bridge_iq/exceptions.py
bridge_iq/logger.py
bridge_iq/models.py
bridge_iq/utils.py
bridge_iq_client-1.0.1.dist-info/licenses/LICENSE
bridge_iq_client-1.0.1.dist-info/METADATA
bridge_iq_client-1.0.1.dist-info/WHEEL
bridge_iq_client-1.0.1.dist-info/top_level.txt
bridge_iq_client-1.0.1.dist-info/RECORD
