Metadata-Version: 2.4
Name: bridge-iq-client
Version: 1.0.1
Summary: Python client for ThakaaMed's imaging AI service
Home-page: https://thakaamed.ai
Author: ThakaaMed
Author-email: contact@thakaamed.com
Project-URL: Bug Tracker, https://github.com/thakaamed/bridge-iq-client/issues
Classifier: Development Status :: 4 - Beta
Classifier: Intended Audience :: Healthcare Industry
Classifier: License :: OSI Approved :: MIT License
Classifier: Programming Language :: Python :: 3
Classifier: Programming Language :: Python :: 3.9
Classifier: Programming Language :: Python :: 3.10
Classifier: Programming Language :: Python :: 3.11
Classifier: Programming Language :: Python :: 3.12
Classifier: Operating System :: OS Independent
Classifier: Topic :: Scientific/Engineering :: Medical Science Apps.
Requires-Python: >=3.9,<3.13
License-File: LICENSE
Requires-Dist: requests>=2.25.0
Requires-Dist: uuid>=1.30
Requires-Dist: platformdirs>=2.0.0
Requires-Dist: httpx>=0.23.0
Requires-Dist: pydantic>=1.9.0
Requires-Dist: python-dateutil>=2.8.2
Provides-Extra: dev
Requires-Dist: pytest>=7.0.0; extra == "dev"
Requires-Dist: black>=22.0.0; extra == "dev"
Requires-Dist: isort>=5.0.0; extra == "dev"
Requires-Dist: mypy>=0.910; extra == "dev"
Requires-Dist: flake8>=4.0.0; extra == "dev"
Requires-Dist: pytest-cov>=3.0.0; extra == "dev"
Dynamic: author
Dynamic: author-email
Dynamic: classifier
Dynamic: description
Dynamic: description-content-type
Dynamic: home-page
Dynamic: license-file
Dynamic: project-url
Dynamic: provides-extra
Dynamic: requires-dist
Dynamic: requires-python
Dynamic: summary
